{
  "gitSyncId": "67efa8d213c5ee130186fbb2_63aa2206-dcf1-4c6d-826b-44e1cd256f94",
  "id": "Users_update_user_status",
  "pluginId": "postgres-plugin",
  "pluginType": "DB",
  "unpublishedAction": {
    "actionConfiguration": {
      "body": "UPDATE \"User\"\nSET status = '{{DropdownStatus.selectedOptionValue}}'\nWHERE \"mobileNumber\" = '{{UsersTable.selectedRow.mobileNumber}}';",
      "encodeParamsToggle": true,
      "paginationType": "NONE",
      "pluginSpecifiedTemplates": [
        {
          "value": true
        }
      ],
      "timeoutInMillisecond": 10000
    },
    "confirmBeforeExecute": false,
    "datasource": {
      "id": "Untitled datasource 1",
      "isAutoGenerated": false,
      "name": "Untitled datasource 1",
      "pluginId": "postgres-plugin"
    },
    "dynamicBindingPathList": [
      {
        "key": "body"
      }
    ],
    "executeOnLoad": false,
    "name": "update_user_status",
    "pageId": "Users",
    "userSetOnLoad": false
  }
}