{
  "gitSyncId": "67efa8d213c5ee130186fbb2_b8542867-fd05-4dc0-9a7b-f6600d4f1431",
  "id": "Users_get_wallet_stats",
  "pluginId": "postgres-plugin",
  "pluginType": "DB",
  "unpublishedAction": {
    "actionConfiguration": {
      "body": "SELECT \n  SUM(\"businessPoints\") as total_business_points,\n  SUM(\"referralPoints\") as total_referral_points,\n  SUM(\"lockedPoints\") as total_locked_points\nFROM \"Wallet\";",
      "encodeParamsToggle": true,
      "paginationType": "NONE",
      "pluginSpecifiedTemplates": [
        {
          "value": true
        }
      ],
      "timeoutInMillisecond": 10000
    },
    "confirmBeforeExecute": false,
    "datasource": {
      "id": "Untitled datasource 1",
      "isAutoGenerated": false,
      "name": "Untitled datasource 1",
      "pluginId": "postgres-plugin"
    },
    "dynamicBindingPathList": [],
    "executeOnLoad": false,
    "name": "get_wallet_stats",
    "pageId": "Users",
    "userSetOnLoad": false
  }
}